nodb/__init__.py
nodb-0.3.2.dist-info/DESCRIPTION.rst
nodb-0.3.2.dist-info/METADATA
nodb-0.3.2.dist-info/RECORD
nodb-0.3.2.dist-info/WHEEL
nodb-0.3.2.dist-info/metadata.json
nodb-0.3.2.dist-info/top_level.txt
