Metadata-Version: 2.0
Name: nodb
Version: 0.3.2
Summary: NoDB isn't a database.. but it sort of looks like one.
Home-page: https://github.com/Miserlou/NoDB
Author: Rich Jones
Author-email: rich@openwatch.net
License: MIT License
Platform: UNKNOWN
Classifier: Environment :: Console
Classifier: License :: OSI Approved :: Apache Software License
Classifier: Operating System :: OS Independent
Classifier: Programming Language :: Python
Classifier: Programming Language :: Python :: 2.7
Classifier: Programming Language :: Python :: 3.5
Classifier: Topic :: Internet :: WWW/HTTP
Classifier: Topic :: Internet :: WWW/HTTP :: Dynamic Content
Requires-Dist: appdirs (==1.4.3)
Requires-Dist: boto3 (==1.4.4)
Requires-Dist: botocore (==1.5.38)
Requires-Dist: coverage (==4.3.4)
Requires-Dist: docutils (==0.13.1)
Requires-Dist: funcsigs (==1.0.2)
Requires-Dist: futures (==3.0.5)
Requires-Dist: jmespath (==0.9.2)
Requires-Dist: nose (==1.3.7)
Requires-Dist: packaging (==16.8)
Requires-Dist: pbr (==2.0.0)
Requires-Dist: pyparsing (==2.2.0)
Requires-Dist: python-dateutil (==2.6.0)
Requires-Dist: s3transfer (==0.1.10)
Requires-Dist: six (==1.10.0)
